target_db2/__init__.py
target_db2/__main__.py
target_db2/connector.py
target_db2/ibm_db_sa/__init__.py
target_db2/ibm_db_sa/base.py
target_db2/ibm_db_sa/ibm_db.py
target_db2/ibm_db_sa/ibm_db_as400.py
target_db2/ibm_db_sa/pyodbc.py
target_db2/ibm_db_sa/reflection.py
target_db2/ibm_db_sa/requirements.py
target_db2/ibm_db_sa/zxjdbc.py
target_db2/target.py
target_db2-0.1.5.dist-info/LICENSE
target_db2-0.1.5.dist-info/METADATA
target_db2-0.1.5.dist-info/WHEEL
target_db2-0.1.5.dist-info/entry_points.txt
target_db2-0.1.5.dist-info/RECORD
