Metadata-Version: 2.1
Name: target-db2
Version: 0.1.5
Summary: `target-db2` is a Singer target for db2, built with the Meltano Singer SDK.
Home-page: https://www.infostrux.com
License: Apache-2.0
Keywords: ELT,IBM,Db2,Singer,Singer Target,Meltano,Meltano SDK
Author: Haleemur Ali
Author-email: haleemur@infostrux.com
Requires-Python: >=3.8,<3.13
Classifier: Intended Audience :: Developers
Classifier: License :: OSI Approved :: Apache Software License
Classifier: Operating System :: OS Independent
Classifier: Programming Language :: Python :: 3
Classifier: Programming Language :: Python :: 3.8
Classifier: Programming Language :: Python :: 3.9
Classifier: Programming Language :: Python :: 3.10
Classifier: Programming Language :: Python :: 3.11
Classifier: Programming Language :: Python :: 3.12
Provides-Extra: s3
Requires-Dist: fs-s3fs (>=1.1.1,<1.2.0) ; extra == "s3"
Requires-Dist: ibm-db (>=3.2.3,<4.0.0)
Requires-Dist: requests (>=2.32.0,<2.33.0)
Requires-Dist: singer-sdk[faker] (>=0.38,<0.41)
Project-URL: Repository, https://github.com/Infostrux-Solutions/target-db2
